{"data":{"allAirtable":{"nodes":[{"data":{"Vaga":"Product Manager","Empresa":"Easynvest","Local":["São Paulo"],"Contato":"https://jobs.lever.co/easynvest/97bc7815-ac48-4db7-8225-6663216edd73?utm_campaign=google_jobs_apply&utm_source=vagascc","Categoria":"Product Management"},"id":"dd7b05ec-463a-546b-8c5a-0df74082765a"},{"data":{"Vaga":"Desevolvedor Web Pleno / Sr.","Empresa":"Elumini","Local":["São Paulo"],"Contato":"http://elumini.enter.jobs/#!/vagas/5dea79eb7318c11300ceb1d3#top","Categoria":"Desenvolvimento"},"id":"e9d5e0c8-0f8b-5a3e-ba5b-40922728949a"},{"data":{"Vaga":"Pessoa Dev iOS Senior","Empresa":"ThoughtWorks","Local":["Recife"],"Contato":"https://grnh.se/6268beca1us","Categoria":"Desenvolvimento"},"id":"bf02d952-9d99-5c51-af30-1048cbe4d01c"},{"data":{"Vaga":"UX Research Manager","Empresa":"Next","Local":["São Paulo"],"Contato":"victor.melo@next.b.br","Categoria":"Design"},"id":"82dee053-bf9d-5a4e-8324-13d6bde1265c"},{"data":{"Vaga":"Designer Gráfico Pleno","Empresa":"Tapps Games","Local":["São Paulo"],"Contato":"https://jobs.kenoby.com/tappsgames/job/designer-grafico-ii/5e583ce602a1a40aa9f6faef","Categoria":"Design"},"id":"a14f8151-384e-5fa2-9817-d80d362a3954"},{"data":{"Vaga":"Analista de Qualidade PL (QA)","Empresa":"KingHost","Local":["Porto Alegre"],"Contato":"https://www.facebook.com/job_opening/879478895843936/","Categoria":"QA"},"id":"92b3484e-1844-50f7-8f30-25baf773f17a"},{"data":{"Vaga":"DevOps","Empresa":"Serasa Consumidor","Local":["Blumenau"],"Contato":"jessica.alves@br.experian.com","Categoria":"Desenvolvimento"},"id":"522f4a35-16b9-5201-9406-47eff7f5ed87"},{"data":{"Vaga":"Product Designer Senior","Empresa":"Next","Local":["São Paulo"],"Contato":"victor.melo@next.b.br","Categoria":"Design"},"id":"f11ee5a8-9880-523c-9a6e-64edcb2e6a6f"},{"data":{"Vaga":"Product Designer Senior","Empresa":"Quero Educação","Local":["São Paulo"],"Contato":"que.bo/uxvagas","Categoria":"Desenvolvimento"},"id":"e952aa61-ee16-59d9-8af6-27a54e6e95f9"},{"data":{"Vaga":"Pessoa Dev Android Senior","Empresa":"ThoughtWorks","Local":["São Paulo"],"Contato":"https://grnh.se/d62477c11","Categoria":"Desenvolvimento"},"id":"32bcbea6-e11d-535b-bf7b-1e8c7a9b3628"},{"data":{"Vaga":"Full Stack","Empresa":"REVEX","Local":["Belo Horizonte"],"Contato":"talentos@optimuminterfaces.com.br","Categoria":"Desenvolvimento"},"id":"bfd031a9-fa9f-5955-9f2f-ec4852d53fb9"},{"data":{"Vaga":"Tech Lead","Empresa":"ZUP Innovation","Local":["Uberlandia","Campinas","São Paulo","Joinville","Belo Horizonte"],"Contato":"https://www.zup.com.br/vagas","Categoria":"Desenvolvimento"},"id":"0ff9ff2b-803a-5e7b-8c4f-c9f2eb675b1b"},{"data":{"Vaga":"PM","Empresa":"CARGOX","Local":["São Paulo"],"Contato":"https://jobs.kenoby.com/cargox","Categoria":"Product Management"},"id":"c2d0bdb4-10aa-575c-b45e-34ab5d63b8d0"},{"data":{"Vaga":"Service Designer Pleno","Empresa":"Next","Local":["São Paulo"],"Contato":"victor.melo@next.b.br","Categoria":"Design"},"id":"5f0c17a4-a502-5c21-aa1c-efbd182f36be"},{"data":{"Vaga":"Tech Lead/Líder Técnico","Empresa":"Easynvest","Local":["São Paulo"],"Contato":"https://jobs.lever.co/easynvest/98c4e66a-a3b4-46ab-9ffa-1f0c7fd5e6f1?utm_campaign=vagascc","Categoria":"Desenvolvimento"},"id":"b52c8eee-ff96-5809-92a5-444aae9559c7"},{"data":{"Vaga":"Diretor de Arte Sênior","Empresa":"Máquina do Bem","Local":["São Paulo"],"Contato":"mdb@maquinadobem.com","Categoria":"Design"},"id":"01325f30-56bd-53fd-a24f-d0dd4dd17968"},{"data":{"Vaga":"Técnico de Infraestrutura PL","Empresa":"KingHost","Local":["Porto Alegre"],"Contato":"https://www.facebook.com/job_opening/2660918440695044/","Categoria":"Desenvolvimento"},"id":"e3ec78a8-306b-5a40-ac1c-7fbd9ec8bdea"},{"data":{"Vaga":"QA Engineer","Empresa":"Novatics","Local":["Brasília"],"Contato":"bit.ly/SelecaoNovatics","Categoria":"QA"},"id":"281decf3-724b-55d3-a98a-4cd2b16acf7a"},{"data":{"Vaga":"DATA SCIENTIST","Empresa":"CARGOX","Local":["São Paulo"],"Contato":"https://cargox.com.br/sobre-nos","Categoria":"Desenvolvimento"},"id":"1e38b772-df16-5828-9f84-95021d8e97c8"},{"data":{"Vaga":"Front end","Empresa":"REVEX","Local":["Belo Horizonte"],"Contato":"talentos@optimuminterfaces.com.br","Categoria":"Desenvolvimento"},"id":"be1bbd2a-32e0-5f25-af9f-583876e00029"},{"data":{"Vaga":"Desenvolvedor(a) Back-end","Empresa":"Easynvest","Local":["São Paulo"],"Contato":"https://jobs.lever.co/easynvest/c2f7a7eb-c2e5-4772-b05c-63f6f9d3f5ec?utm_campaign=google_jobs_apply&utm_source=vagascc","Categoria":"Desenvolvimento"},"id":"37c6944d-53c3-5961-b413-99b3a4355d0a"},{"data":{"Vaga":"iOS","Empresa":"ZUP Innovation","Local":["Uberlandia","Campinas","São Paulo","Joinville","Belo Horizonte"],"Contato":"https://www.zup.com.br/vagas","Categoria":"Desenvolvimento"},"id":"659d0538-860f-5a5b-949a-e1ea1a73c4cf"},{"data":{"Vaga":"Tech Lead ","Empresa":"Foursys","Local":["São Paulo"],"Contato":"recrutamento.unidade2@foursys.com.br","Categoria":"Desenvolvimento"},"id":"42f33132-786c-58a1-aea4-a81455971e4f"},{"data":{"Vaga":"SOFTWARE ENGINEER","Empresa":"CARGOX","Local":["São Paulo"],"Contato":"https://jobs.kenoby.com/cargox","Categoria":"Desenvolvimento"},"id":"87fde58f-de8f-5423-ae76-d293311af8c6"},{"data":{"Vaga":"UI/UX Designer","Empresa":"Origin","Local":["São Paulo"],"Contato":"joao@useorigin.com","Categoria":"Design"},"id":"9e256acc-2cec-5c12-a082-f5f66c69187f"},{"data":{"Vaga":"Visual Designer","Empresa":"Zenvia","Local":["Porto Alegre"],"Contato":"https://zenvia.gupy.io/","Categoria":"Design"},"id":"dae11058-e7fc-5275-9940-7ef061ee0c41"},{"data":{"Vaga":"Product Owner","Empresa":"Serasa Consumidor","Local":["Blumenau"],"Contato":"jessica.alves@br.experian.com","Categoria":"Product Management"},"id":"6c909053-fe15-5ee4-8dab-ba44dec2e4b8"},{"data":{"Vaga":"Frontend Developer (React Native, React, Angular)","Empresa":"Serasa Consumidor","Local":["Blumenau"],"Contato":"jessica.alves@br.experian.com","Categoria":"Desenvolvimento"},"id":"358c7e77-6e2d-5b46-befb-572d2fd2169f"},{"data":{"Vaga":"Product Designer Pleno","Empresa":"Vet Smart / Petlove","Local":["São Paulo"],"Contato":"vinicius@vetsmart.com.br","Categoria":"Design"},"id":"30114701-52bd-505a-b1b6-fefc07f113a3"},{"data":{"Vaga":"Desenvolvedor(a) Full Stack ","Empresa":"ZUP","Local":["São Paulo"],"Contato":"https://apply.workable.com/zup/j/F8F3043988/","Categoria":"Desenvolvimento"},"id":"fdbe2649-8cc1-5a34-85b1-4c6de762d5ff"},{"data":{"Vaga":"Desenvolvedor(a) Node.JS","Empresa":"ZUP","Local":["São Paulo"],"Contato":"https://apply.workable.com/zup/j/92D8C42F29/","Categoria":"Desenvolvimento"},"id":"966e93b8-fc0f-5404-b89a-a0a349618d7b"},{"data":{"Vaga":"Pessoa Dev Designer de UX - Trainee","Empresa":"ThoughtWorks","Local":["Recife"],"Contato":"https://grnh.se/69f676951us","Categoria":"Desenvolvimento"},"id":"919333d2-5038-5489-aa66-a10b4bba1ec0"},{"data":{"Vaga":"SRE/DevOps Engineer","Empresa":"Delivery Much","Local":["Florianópolis"],"Contato":"https://jobs.kenoby.com/deliverymuch/job/sredevops-engineer-2-vagas/5e66a1565f1ddb79a11d61a1","Categoria":"Desenvolvimento"},"id":"a226e5d2-d744-5575-93df-285b95a29a3d"},{"data":{"Vaga":"Desenvolvedor(a) Python  - Remoto","Empresa":"Olist","Local":["Remoto"],"Contato":"https://olist.gupy.io/jobs/98275","Categoria":"Desenvolvimento"},"id":"f573a98c-e52b-5c53-bc1c-e8100b38d111"},{"data":{"Vaga":"Pessoa Dev Designer de UX - Trainee","Empresa":"ThoughtWorks","Local":["São Paulo"],"Contato":"https://grnh.se/f26881551us","Categoria":"Desenvolvimento"},"id":"bf58e0e6-a6aa-5b6b-954f-9bddd8a85a1f"},{"data":{"Vaga":"Pessoa Dev Front-end Senior","Empresa":"ThoughtWorks","Local":["Belo Horizonte"],"Contato":"https://grnh.se/19a3b0321us","Categoria":"Desenvolvimento"},"id":"450dab5b-f1d9-5c87-a7e8-0c30f64bbd82"},{"data":{"Vaga":"Data Analyst","Empresa":"Sanar","Local":["Salvador","São Paulo","Remoto"],"Contato":"https://jobs.kenoby.com/sanar/job/data-analyst/5e8a69b1cd2ae2745d86e4fc","Categoria":"Desenvolvimento"},"id":"a5839d62-eca2-535c-89ec-e25c9b1724ac"},{"data":{"Vaga":"Engenheiro de Dados","Empresa":"Geofusion","Local":["São Paulo"],"Contato":"https://www.vagas.com.br/empregos/geofusion","Categoria":"Desenvolvimento"},"id":"c05716de-fd5e-55be-97f9-23fe257199a5"},{"data":{"Vaga":"UX/UI","Empresa":"Stefanini","Local":["Belo Horizonte"],"Contato":"ruda.martins@ihm.com.br","Categoria":"Design"},"id":"86a1adb0-a794-57d7-a0cc-0c98d51b9ff2"},{"data":{"Vaga":"Pessoa Dev Android Senior","Empresa":"ThoughtWorks","Local":["Recife"],"Contato":"https://grnh.se/1391fb221us","Categoria":"Desenvolvimento"},"id":"5388696f-735d-5bf8-8f4f-4c17d0ad40af"},{"data":{"Vaga":"Back End Sênior","Empresa":"Sanar","Local":["Salvador","São Paulo","Remoto"],"Contato":"https://jobs.kenoby.com/sanar/job/desenvolvedora-back-end-senior-sanar-medicina/5e2a295f41196a772f536642","Categoria":"Desenvolvimento"},"id":"70297d16-1c5c-560c-8844-f205a2ca77a3"},{"data":{"Vaga":"UI Designer Pleno","Empresa":"Serasa Consumidor","Local":["Blumenau"],"Contato":"jessica.alves@br.experian.com","Categoria":"Design"},"id":"f3021793-ce71-5d8e-94bd-cdc05cf3ddad"},{"data":{"Vaga":"Pessoa Dev Front-end Pleno","Empresa":"ThoughtWorks","Local":["Porto Alegre"],"Contato":"https://grnh.se/cb1b20241us","Categoria":"Desenvolvimento"},"id":"e58467c6-34b6-5d86-ba73-c021101b0a23"},{"data":{"Vaga":"UI/UX designer","Empresa":"Serasa Consumidor","Local":["Blumenau","São Paulo"],"Contato":"jessica.alves@br.experian.com","Categoria":"Design"},"id":"da8bbec4-e8d8-5bce-80ee-0c65f6ba485f"},{"data":{"Vaga":"DevOps","Empresa":"Sciensa","Local":["São Paulo"],"Contato":"https://jobs.lever.co/sciensa/46b22b79-7f94-4b52-b237-056ab7d00c26","Categoria":"Desenvolvimento"},"id":"afe4896e-4b96-5cc8-bd9e-103132cf3eb1"},{"data":{"Vaga":"UI/UX Designer","Empresa":"Novatics","Local":["Brasília"],"Contato":"bit.ly/SelecaoNovatics","Categoria":"Design"},"id":"63d31a51-ac64-51cb-9746-25b8f0fba89f"},{"data":{"Vaga":"Product Manager ","Empresa":"Delivery Much","Local":["Florianópolis"],"Contato":"https://jobs.kenoby.com/deliverymuch/job/product-manager/5e7f9ba475ae9b3dd1e32513","Categoria":"Product Management"},"id":"5d223db3-ef89-53ec-a579-edea8de4b471"},{"data":{"Vaga":"Mobile Pleno","Empresa":"Sanar","Local":["Salvador","São Paulo","Remoto"],"Contato":"https://jobs.kenoby.com/sanar/job/desenvolvedora-mobile-react-native-pleno/5e5583d50f5c1c505aad9d4f","Categoria":"Desenvolvimento"},"id":"a3b38ffd-9f88-5538-805a-3df54d2b6e3f"},{"data":{"Vaga":"Dev Back End","Empresa":"Grupo Boticário","Local":["São Paulo","Curitiba"],"Contato":"https://www.eufacobonito.com.br/","Categoria":"Desenvolvimento"},"id":"00b7440f-399a-5122-a803-6e72cfa2ba0e"},{"data":{"Vaga":"UX/UI","Empresa":"REVEX","Local":["Belo Horizonte"],"Contato":"talentos@optimuminterfaces.com.br","Categoria":"Design"},"id":"a826cb17-0169-5851-a5d3-99402d90216f"},{"data":{"Vaga":"Product Owner Pleno","Empresa":"CARGOX","Local":["São Paulo"],"Contato":"https://jobs.kenoby.com/cargox","Categoria":"Product Management"},"id":"bb5b6429-c15a-504c-b60d-9c7bf94d4f49"},{"data":{"Vaga":"Pessoa Dev iOS Senior","Empresa":"ThoughtWorks","Local":["Porto Alegre"],"Contato":"https://grnh.se/8a297fa21us","Categoria":"Desenvolvimento"},"id":"2da1640b-8997-5c3b-8de6-a2cee61b9703"},{"data":{"Vaga":"Pessoa Dev Front-end Senior","Empresa":"ThoughtWorks","Local":["São Paulo"],"Contato":"https://grnh.se/969c94d41us","Categoria":"Desenvolvimento"},"id":"35741163-9543-50d9-bbd2-35ffd98ebd7b"},{"data":{"Vaga":"Analista de produto","Empresa":"Bradesco","Local":["São José dos Campos"],"Contato":"marcel.marques@bradesco.com.br","Categoria":"Outras"},"id":"634bf8e2-7561-50e5-aac9-401e100c35dc"},{"data":{"Vaga":"Cyber Security","Empresa":"Serasa Consumidor","Local":["São Paulo"],"Contato":"jessica.alves@br.experian.com","Categoria":"Desenvolvimento"},"id":"73109f6d-859f-5a45-8121-de2fbda89ab5"},{"data":{"Vaga":"Pessoa Dev Back-end Senior","Empresa":"ThoughtWorks","Local":["Belo Horizonte"],"Contato":"https://grnh.se/ee31838d1us","Categoria":"Desenvolvimento"},"id":"2c345adb-2cb6-5e4f-82ca-f914ebcd237a"},{"data":{"Vaga":"AI Manager","Empresa":"Nubank","Local":["São Paulo","Cidade do México","Buenos Aires"],"Contato":"https://boards.greenhouse.io/nubank","Categoria":"Product Management"},"id":"fd2f0816-7818-5a1e-8593-b169df271e7c"},{"data":{"Vaga":"Desenvolvedor JAVA JR, PLENO E SR","Empresa":"RD (RAIA DROGASIL)","Local":["São Paulo"],"Contato":"arigon@rd.com.br","Categoria":"Desenvolvimento"},"id":"30bff922-49c1-5d0d-b0fc-4ef5d11c1347"},{"data":{"Vaga":"Tech Lead","Empresa":"Grupo Boticário","Local":["Curitiba"],"Contato":"https://www.eufacobonito.com.br/","Categoria":"Desenvolvimento"},"id":"76486aea-669b-5cd7-8fac-c4b8eeecfeb5"},{"data":{"Vaga":"Estágio de Desenvolvimento","Empresa":"Sanar","Local":["Salvador","São Paulo","Remoto"],"Contato":"https://jobs.kenoby.com/sanar/job/estagiari-de-desenvolvimento/5e4d29397f4ab8441aac35d9","Categoria":"Desenvolvimento"},"id":"3ebd4b7f-530e-51da-8d84-977b66881d20"},{"data":{"Vaga":"Back-End (Java, GO e .NET Core)","Empresa":"ZUP Innovation","Local":["Uberlandia","Campinas","São Paulo","Joinville","Belo Horizonte"],"Contato":"https://www.zup.com.br/vagas","Categoria":"Desenvolvimento"},"id":"0baf27cd-457a-5975-9ad7-baac8febf893"},{"data":{"Vaga":"Desenvolvedor (a) Mobile - Remoto","Empresa":"Olist","Local":["Remoto"],"Contato":"https://olist.gupy.io/jobs/98278","Categoria":"Desenvolvimento"},"id":"f9732152-8c22-51d4-86da-7ad0cbd269ba"},{"data":{"Vaga":"Senior Product Designer","Empresa":"Nubank","Local":["São Paulo","Cidade do México","Buenos Aires"],"Contato":"https://boards.greenhouse.io/nubank","Categoria":"Design"},"id":"9becba3f-52f2-5b71-96e5-5778033d388c"},{"data":{"Vaga":"Product Designer Senior","Empresa":"Quero Educação","Local":["São José dos Campos"],"Contato":"que.bo/uxvagas","Categoria":"Design"},"id":"37d21f4b-f921-519c-aefa-5d6733c15cf0"},{"data":{"Vaga":"Design Ops","Empresa":"Quero Educação","Local":["São José dos Campos"],"Contato":"que.bo/uxvagas","Categoria":"Design"},"id":"3a0e7245-141c-583e-8965-5ba827ad8512"},{"data":{"Vaga":"Dev. .Net Core ","Empresa":"Sciensa","Local":["São Paulo"],"Contato":"https://jobs.lever.co/sciensa/1ad9c71b-d53d-4225-9eaa-1f144c762af2","Categoria":"Desenvolvimento"},"id":"89b9de69-75c3-5309-9e56-2bdb8e00706e"},{"data":{"Vaga":"Pessoa Dev Back-end Lead","Empresa":"ThoughtWorks","Local":["São Paulo"],"Contato":"https://grnh.se/ccabe3e21us","Categoria":"Desenvolvimento"},"id":"4cff8482-6de1-5987-bc09-c3c0145bf843"},{"data":{"Vaga":"Analista de QA ","Empresa":"Easynvest","Local":["São Paulo"],"Contato":"https://jobs.lever.co/easynvest/a4fb415a-d8f2-4de0-8bbc-fae6e27ef9b8?utm_campaign=google_jobs_apply&utm_source=vagascc","Categoria":"QA"},"id":"ff3a8ed8-ddb4-5e82-85eb-fcf394ce33bf"},{"data":{"Vaga":"UX/UI Designer ","Empresa":"ZUP","Local":["São Paulo"],"Contato":"https://apply.workable.com/zup/j/F49C0FEFC1/","Categoria":"Design"},"id":"b06abaff-2bfe-5262-82ed-54fb6579510b"},{"data":{"Vaga":"Designer","Empresa":"Delivery Much","Local":["Florianópolis"],"Contato":"https://jobs.kenoby.com/deliverymuch/job/designer/5e7de15392d268798e35fc9a","Categoria":"Design"},"id":"064670bb-2002-5001-87af-b8b4312a04e2"},{"data":{"Vaga":"Dev PCD","Empresa":"Grupo Boticário","Local":["São Paulo","Curitiba"],"Contato":"https://www.eufacobonito.com.br/","Categoria":"Desenvolvimento"},"id":"f33eae83-f96a-551c-9999-7e15d1bba86e"},{"data":{"Vaga":"Mobile Sênior","Empresa":"Sanar","Local":["Salvador","São Paulo","Remoto"],"Contato":"https://jobs.kenoby.com/sanar/job/desenvolvedora-mobile-react-native-senior/5e5585651a14202186c404ef","Categoria":"Desenvolvimento"},"id":"f4208072-07e8-5bff-a49c-28295019afba"},{"data":{"Vaga":"Pessoa Dev iOS Pleno","Empresa":"ThoughtWorks","Local":["Recife"],"Contato":"https://grnh.se/1b654f3d1us","Categoria":"Desenvolvimento"},"id":"e9593913-b71c-5b86-aaa4-7daf4125ead1"},{"data":{"Vaga":"User Experience Designer","Empresa":"Motorola","Local":["São Paulo"],"Contato":"https://lenovocareers.com/areas-mobile.html#search","Categoria":"Design"},"id":"107ba755-da8f-53d3-b6cc-5e4eb20e9161"},{"data":{"Vaga":"Pessoa Dev Back-end Pleno","Empresa":"ThoughtWorks","Local":["São Paulo"],"Contato":"https://grnh.se/e973f4731us","Categoria":"Desenvolvimento"},"id":"1c24c3a0-1482-5d81-a051-b4105be9e08c"},{"data":{"Vaga":"QA Analyst","Empresa":"Serasa Consumidor","Local":["Blumenau"],"Contato":"jessica.alves@br.experian.com","Categoria":"QA"},"id":"cc42ba75-83bf-5fe8-88c3-de6d3d94878a"},{"data":{"Vaga":"Backend Developer (Java, Python, Node.js, PHP)","Empresa":"Serasa Consumidor","Local":["Blumenau","São Paulo"],"Contato":"jessica.alves@br.experian.com","Categoria":"Desenvolvimento"},"id":"fb140473-c4ad-56aa-996b-644aa18ae822"},{"data":{"Vaga":"Product Designer Senior","Empresa":"D3","Local":["São Paulo"],"Contato":"https://apply.workable.com/thegrid/j/325CDA3B55/","Categoria":"Design"},"id":"f3b282ee-0ec8-5b66-bdf7-8fdf5b0dc063"},{"data":{"Vaga":"Analista de Remuneração","Empresa":"Easynvest","Local":["São Paulo"],"Contato":"https://jobs.lever.co/easynvest/8fae9f75-a8ca-4f28-a059-af3ca04cb033?utm_campaign=vagascc","Categoria":"Outras"},"id":"79429b37-a057-58a5-9fe7-db5482291865"},{"data":{"Vaga":"Developer ","Empresa":"PRAVALER ","Local":["São Paulo"],"Contato":"https://jobs.kenoby.com/pravaler/job/developer/5e3c5847f3fe0e3d05127f04","Categoria":"Desenvolvimento"},"id":"cbf698f7-4d39-56f3-8466-d8b720b5a1bd"},{"data":{"Vaga":"Senior Visual Designer","Empresa":"Kaspersky","Local":["São Paulo"],"Contato":"https://careers.kaspersky.com/vacancy/3707/","Categoria":"Design"},"id":"ee43241a-7218-5d75-a7e7-8cdde7e85dcc"},{"data":{"Vaga":"Software Engineer","Empresa":"Novatics","Local":["Brasília"],"Contato":"bit.ly/SelecaoNovatics","Categoria":"Desenvolvimento"},"id":"edaf11f6-ac52-52b0-af70-060e37783ac5"},{"data":{"Vaga":"Pessoa Dev iOS Pleno","Empresa":"ThoughtWorks","Local":["Porto Alegre"],"Contato":"https://grnh.se/dfb059a51us","Categoria":"Desenvolvimento"},"id":"cf385a5f-d473-53a4-b6af-e1399f41f9d7"},{"data":{"Vaga":"Analista de Comunicação Interna Plena(o)","Empresa":"Easynvest","Local":["São Paulo"],"Contato":"https://jobs.lever.co/easynvest/f0dbda9f-e736-4fe0-a64f-c9e9a0f0e1fd?utm_campaign=vagascc","Categoria":"Outras"},"id":"d6396fc3-4866-5e6f-8d4b-5643c0afd1ef"},{"data":{"Vaga":"Pessoa Dev Front-end Senior","Empresa":"ThoughtWorks","Local":["Recife"],"Contato":"https://grnh.se/f2777e211us","Categoria":"Desenvolvimento"},"id":"a86a6c35-b540-5e44-8007-5f8b536ba131"},{"data":{"Vaga":"Product Designer Pleno","Empresa":"Quero Educação","Local":["São José dos Campos"],"Contato":"que.bo/uxvagas","Categoria":"Design"},"id":"bb913845-82a4-5d4b-aa2c-5e8325e04b18"},{"data":{"Vaga":"Engenheiro de Dados","Empresa":"Zenvia","Local":["Porto Alegre"],"Contato":"https://zenvia.gupy.io/","Categoria":"Desenvolvimento"},"id":"14eb3182-c11f-5c32-8a9e-8236bd0a7042"},{"data":{"Vaga":"Desenvolvedor(a) Frontend","Empresa":"Easynvest","Local":["São Paulo"],"Contato":"https://www.linkedin.com/jobs/view/desenvolvedor-frontend-at-easynvest-1808635342/?utm_campaign=google_jobs_apply&utm_source=google_jobs_apply&utm_medium=vagascc","Categoria":"Desenvolvimento"},"id":"48b109ea-dcc8-5d5a-b32c-6cd6264b0aba"},{"data":{"Vaga":"Pessoa Dev Front-end Pleno","Empresa":"ThoughtWorks","Local":["Belo Horizonte"],"Contato":"https://grnh.se/98378b261us","Categoria":"Desenvolvimento"},"id":"cc09fa9a-2eb4-50bd-8e51-be6d27a0d511"},{"data":{"Vaga":"Desenvolvedor/Desenvolvedora Frontend","Empresa":"Delivery Much","Local":["Florianópolis"],"Contato":"https://jobs.kenoby.com/deliverymuch/job/desenvolvedordesenvolvedora-frontend-2-vagas/5e81c9f8ce6c5e57ba34b1b5","Categoria":"Desenvolvimento"},"id":"180d24e3-c705-56dc-ac73-6dca18e23f81"},{"data":{"Vaga":"UX Junior","Empresa":"Agilize Contabilidade Online","Local":["Bahia"],"Contato":"laert@agilize.com.br","Categoria":"Design"},"id":"863d113b-f03e-5dc2-9be2-c29d50b9c5b6"},{"data":{"Vaga":"Java Developer","Empresa":"Sciensa","Local":["São Paulo"],"Contato":"https://jobs.lever.co/sciensa/13a994b2-3f4f-47ab-b19e-a39b49bcb25f","Categoria":"Desenvolvimento"},"id":"59540eb7-f92e-5a11-93a0-f8b380e8ba23"},{"data":{"Vaga":"Product Manager","Empresa":"Nubank","Local":["São Paulo","Cidade do México","Buenos Aires"],"Contato":"https://boards.greenhouse.io/nubank","Categoria":"Product Management"},"id":"e95e382c-0c8b-5a8f-8da9-97db396ea03a"},{"data":{"Vaga":"Coordenador(a) de Campanhas Digitais","Empresa":"Easynvest","Local":["São Paulo"],"Contato":"https://jobs.lever.co/easynvest/a0530acc-c383-4995-8ea6-8010601e6e66?utm_campaign=vagascc","Categoria":"Outras"},"id":"e88f339e-a2df-5af3-8689-e2c6065657db"},{"data":{"Vaga":"UX Designer Senior","Empresa":"IBM/Decision","Local":["São Paulo"],"Contato":"vanessab@br.ibm.com","Categoria":"Design"},"id":"3a2f2995-6176-545d-b95a-c39f9966079c"},{"data":{"Vaga":"Senior UX Designer","Empresa":"Sidia","Local":["Manaus"],"Contato":"wilson.prata@sidia.com","Categoria":"Design"},"id":"94cbc3d4-9bc2-5d93-a0a2-42b90c63c7ed"},{"data":{"Vaga":"Frontend Developer (React Native, React ou Angular)","Empresa":"Serasa Consumidor","Local":["Blumenau"],"Contato":"serasaconsumidor.com.br/carreiras","Categoria":"Desenvolvimento"},"id":"21bdd2bc-20cc-5c8b-8228-712fa3b02288"},{"data":{"Vaga":"PM - PRODUCT MANAGER - SÊNIOR","Empresa":"CARGOX","Local":["São Paulo"],"Contato":"https://jobs.kenoby.com/cargox","Categoria":"Product Management"},"id":"6dc0a856-2b42-5fe3-8424-2bb9527e32a9"},{"data":{"Vaga":"QA - ANALISTA DE TESTES PLENO","Empresa":"CARGOX","Local":["São Paulo"],"Contato":"https://jobs.kenoby.com/cargox","Categoria":"QA"},"id":"dd5598c2-c7db-5b17-a47f-b151be58d5dc"},{"data":{"Vaga":"Fullstack Developer","Empresa":"Sciensa","Local":["São Paulo"],"Contato":"https://jobs.lever.co/sciensa/1b01f503-9371-4b51-a807-6860f36574e4","Categoria":"Desenvolvimento"},"id":"9ed6b15a-4dcf-56e1-8141-68ff38c16b24"},{"data":{"Vaga":"Design Manager","Empresa":"Nubank","Local":["São Paulo","Cidade do México","Buenos Aires"],"Contato":"https://boards.greenhouse.io/nubank","Categoria":"Design"},"id":"b890fff7-3540-57bb-9a6d-d261b09a2255"},{"data":{"Vaga":"Software Engineer","Empresa":"Serasa Consumidor","Local":["Blumenau"],"Contato":"jessica.alves@br.experian.com","Categoria":"Desenvolvimento"},"id":"5125ff9a-3f8d-5b9d-a671-53d373ac36fe"},{"data":{"Vaga":"Senior Software Engineer","Empresa":"Intuit","Local":["São Paulo"],"Contato":"https://www.linkedin.com/jobs/view/1816111343","Categoria":"Desenvolvimento"},"id":"4a388b1a-8db6-58bd-aee9-1c0ca238af07"},{"data":{"Vaga":"Pessoa Dev Back-end Senior","Empresa":"ThoughtWorks","Local":["Porto Alegre"],"Contato":"https://grnh.se/3ff1ed991us","Categoria":"Desenvolvimento"},"id":"fcebad7b-f252-5759-9491-690dacaeb667"},{"data":{"Vaga":"Service Designer Senior","Empresa":"Next","Local":["São Paulo"],"Contato":"victor.melo@next.b.br","Categoria":"Design"},"id":"669cfa23-3674-5057-8d35-afb2c2cc06e5"},{"data":{"Vaga":"Pessoa Dev Android Pleno","Empresa":"ThoughtWorks","Local":["Recife"],"Contato":"https://grnh.se/d31090591us","Categoria":"Desenvolvimento"},"id":"2906b3b8-17ca-5c30-9508-54448a11579d"},{"data":{"Vaga":"Pessoa Dev iOS Senior","Empresa":"ThoughtWorks","Local":["Belo Horizonte"],"Contato":"https://grnh.se/6289ad2c1us","Categoria":"Desenvolvimento"},"id":"1e183e53-a8e2-519d-aa92-fb1c1f5f74b5"},{"data":{"Vaga":"Desenvolvedor(a) iOS ","Empresa":"ZUP","Local":["São Paulo"],"Contato":"https://apply.workable.com/zup/j/59CF3976C8/","Categoria":"Desenvolvimento"},"id":"a8ce24dc-6096-546c-8953-ec781d3688c2"},{"data":{"Vaga":"UX sênior ","Empresa":"Sempre IT","Local":["São Paulo"],"Contato":"contato@sempreit.com.br","Categoria":"Design"},"id":"50fb8e88-a94c-557a-8679-268a60f59e88"},{"data":{"Vaga":"Senior Product Designer ","Empresa":"Easynvest","Local":["São Paulo"],"Contato":"https://jobs.lever.co/easynvest/d987e813-1a64-42a6-ba4c-cb83d5709c84?utm_campaign=google_jobs_apply&utm_source=vagascc","Categoria":"Design"},"id":"ab945af3-4d7c-5079-ab8a-f9f5ebf1036b"},{"data":{"Vaga":"UX designer","Empresa":"Serasa Consumidor","Local":["Blumenau"],"Contato":"jessica.alves@br.experian.com","Categoria":"Design"},"id":"2113ee86-6c15-555b-9872-777b033e4032"},{"data":{"Vaga":"Pessoa Dev Back-end Senior","Empresa":"ThoughtWorks","Local":["Recife"],"Contato":"https://grnh.se/85e530cb1us","Categoria":"Desenvolvimento"},"id":"51486e2b-fa99-5a49-847a-c15019e9c0c9"},{"data":{"Vaga":"Android Developer","Empresa":"Serasa Consumidor","Local":["Blumenau","São Paulo"],"Contato":"jessica.alves@br.experian.com","Categoria":"Desenvolvimento"},"id":"9b2f2d06-eaba-588a-ae5c-1a24b80cd085"},{"data":{"Vaga":"Arquiteto(a) Web & Mobile","Empresa":"ZUP","Local":["São Paulo"],"Contato":"https://apply.workable.com/zup/j/F95AD10C4C/apply/","Categoria":"Desenvolvimento"},"id":"2afbcfea-62f1-58ba-8674-7ad977c8d844"},{"data":{"Vaga":"Analista de SEO","Empresa":"Conube","Local":["São Paulo"],"Contato":"https://jobs.solides.com/Conube/vaga/22431","Categoria":"SEO"},"id":"c565a94b-0fc3-5ada-ad39-431c8001d5dd"},{"data":{"Vaga":"UX/UI- PLENO","Empresa":"Ânima Educação","Local":["São Paulo"],"Contato":"ana.moino@animaeducacao.com.br","Categoria":"Design"},"id":"0a7c35ea-92b6-5d44-9334-b4ffe117a01a"},{"data":{"Vaga":"Product Manager ","Empresa":"Serasa Consumidor","Local":["São Paulo"],"Contato":"serasaconsumidor.com.br/carreiras","Categoria":"Product Management"},"id":"d574fb0f-95ab-5eae-b01a-0dc7b16abae1"},{"data":{"Vaga":"Coordenador de Design","Empresa":"Bemobi","Local":["Rio de Janeiro"],"Contato":"linkedin.com/jobs/view/1813305509/","Categoria":"Design"},"id":"b96f64ff-c286-5305-b389-6f8e0a76caac"},{"data":{"Vaga":"UX Lead","Empresa":"Next","Local":["São Paulo"],"Contato":"victor.melo@next.b.br","Categoria":"Design"},"id":"427f92ef-16e7-5995-95c2-32fac58b2c74"},{"data":{"Vaga":"Gerente de Dados","Empresa":"Olist","Local":["Curitiba"],"Contato":"https://olist.gupy.io/jobs/181195","Categoria":"Desenvolvimento"},"id":"f4292cd9-0793-591b-8165-33be04b2fd4d"},{"data":{"Vaga":"Android","Empresa":"ZUP Innovation","Local":["Uberlandia","Campinas","São Paulo","Joinville","Belo Horizonte"],"Contato":"https://www.zup.com.br/vagas","Categoria":"Desenvolvimento"},"id":"150021fa-f393-5769-9c95-eaa67743be27"},{"data":{"Vaga":"ANDROID","Empresa":"CARGOX","Local":["São Paulo"],"Contato":"https://jobs.kenoby.com/cargox","Categoria":"Desenvolvimento"},"id":"03b5f46a-17e2-5b7f-af61-8ddb5d6e3fcd"},{"data":{"Vaga":"Desenvolvedor(a) Mobile - Presencial","Empresa":"Olist","Local":["Curitiba","São Paulo"],"Contato":"https://olist.gupy.io/jobs/143009","Categoria":"Desenvolvimento"},"id":"9fa09a9c-2c3e-584f-a45d-e4a7f5fbad7b"},{"data":{"Vaga":"Front & Back-end Software Engineer, todos os níveis","Empresa":"Origin","Local":["São Paulo"],"Contato":"joao@useorigin.com","Categoria":"Desenvolvimento"},"id":"f445e1af-b2d7-50fd-b69a-6749b82d8146"},{"data":{"Vaga":"Pessoa Dev Back-end Pleno","Empresa":"ThoughtWorks","Local":["Porto Alegre"],"Contato":"https://grnh.se/c2bbfcfb1us","Categoria":"Desenvolvimento"},"id":"07260c96-29cd-5086-9678-1c8a623b970f"},{"data":{"Vaga":"Pessoa Dev Back-end Senior","Empresa":"ThoughtWorks","Local":["São Paulo"],"Contato":"https://grnh.se/2282f5a21us","Categoria":"Desenvolvimento"},"id":"a34246d4-6122-50d7-90db-020935d942ef"},{"data":{"Vaga":"Desenvolvedor(a) Android","Empresa":"ZUP","Local":["São Paulo"],"Contato":"https://apply.workable.com/zup/j/6184AF0149/","Categoria":"Desenvolvimento"},"id":"e7f32fab-5f7d-53f5-885a-f5b3a8bed763"},{"data":{"Vaga":"Pessoa Dev Back-end Pleno","Empresa":"ThoughtWorks","Local":["Recife"],"Contato":"https://grnh.se/9c2e724d1us","Categoria":"Desenvolvimento"},"id":"e80863c4-181c-5221-821b-e3ba93b53148"},{"data":{"Vaga":"Mobile Jr","Empresa":"Sanar","Local":["Salvador","São Paulo","Remoto"],"Contato":"https://jobs.kenoby.com/sanar/job/desenvolvedora-mobile-react-native-junior/5e55811fb9d937502929aafe","Categoria":"Desenvolvimento"},"id":"b511131f-9834-5fd6-8b2a-70ffa3b5dce3"},{"data":{"Vaga":"Pessoa Dev iOS Pleno","Empresa":"ThoughtWorks","Local":["Belo Horizonte"],"Contato":"https://grnh.se/f4ed17851us","Categoria":"Desenvolvimento"},"id":"1b5188bc-83a1-559c-a0d7-76ce57d0626e"},{"data":{"Vaga":"Pessoa Dev Android Senior","Empresa":"ThoughtWorks","Local":["Porto Alegre"],"Contato":"https://grnh.se/7744ce191us","Categoria":"Desenvolvimento"},"id":"3acba373-afe6-56fc-9cf9-45b6b6b9bd17"},{"data":{"Vaga":"Game Artist Pleno","Empresa":"Tapps Games","Local":["São Paulo"],"Contato":"https://jobs.kenoby.com/tappsgames/job/game-artist-ii/5e6922485a068321f4b09fa1","Categoria":"Design"},"id":"8b30a912-9a96-5b44-9865-011c0d714500"},{"data":{"Vaga":"Product Manager","Empresa":"Serasa Consumidor","Local":["São Paulo"],"Contato":"jessica.alves@br.experian.com","Categoria":"Product Management"},"id":"a1ef8fae-c335-5926-a85a-b9660584140e"},{"data":{"Vaga":"DATA SCIENTIST SÊNIOR","Empresa":"CARGOX","Local":["São Paulo"],"Contato":"https://jobs.kenoby.com/cargox","Categoria":"Desenvolvimento"},"id":"85041bca-7d03-5378-a6cc-0a699f67b738"},{"data":{"Vaga":"Back End Java","Empresa":"The Hive Brasil","Local":["São Paulo"],"Contato":"https://www.linkedin.com/jobs/view/1766882829/?refId=1350387711585962361819&trk=d_flagship3_company","Categoria":"Desenvolvimento"},"id":"867d77ca-5c53-54be-abc6-c76797103c18"},{"data":{"Vaga":"Product Design Lead","Empresa":"Easynvest","Local":["São Paulo"],"Contato":"https://jobs.lever.co/easynvest/d806b805-c4e2-4af5-8884-234ad84c171a?utm_campaign=google_jobs_apply&utm_source=vagascc","Categoria":"Design"},"id":"2106954e-8d87-59bd-837a-ab0206fa7d4f"},{"data":{"Vaga":"QA Analyst","Empresa":"Sanar","Local":["Salvador","São Paulo","Remoto"],"Contato":"https://jobs.kenoby.com/sanar/job/qa-analyst/5e8a6efb09317d74f0c995bd","Categoria":"QA"},"id":"ece33b83-a40b-5a6d-bc9b-8ad708e00daa"},{"data":{"Vaga":"Product Designer Pl e Sr","Empresa":"PicPay","Local":["São Paulo"],"Contato":"https://picpay.gupy.io/jobs/180135","Categoria":"Design"},"id":"8bff264f-eb80-5a02-bbaf-08e68234fe74"},{"data":{"Vaga":"Front End Jr","Empresa":"Sanar","Local":["Salvador","São Paulo","Remoto"],"Contato":"https://jobs.kenoby.com/sanar/job/desenvolvedora-front-end-junior-sanar-medicina/5e3210d2d624ee4a051829eb","Categoria":"Desenvolvimento"},"id":"adde61c1-3226-5ffe-82e7-2555b4f0a8fa"},{"data":{"Vaga":"Desenvolvedor PLSQL Pleno","Empresa":"Kstack","Local":["São Paulo"],"Contato":"ingrid.silvestre@kstack.com.br","Categoria":"Desenvolvimento"},"id":"f44f5820-dd9e-5128-a15c-e8174f34d1c2"},{"data":{"Vaga":"Back End Pleno","Empresa":"Sanar","Local":["Salvador","São Paulo","Remoto"],"Contato":"https://jobs.kenoby.com/sanar/job/desenvolvedora-back-end-pleno-sanar-medicina/5e2a1c8831df3013e37031e9","Categoria":"Desenvolvimento"},"id":"48423a02-a224-568a-bd86-6b40ed277afd"},{"data":{"Vaga":"DevOps","Empresa":"Serasa Consumidor","Local":["Blumenau"],"Contato":"serasaconsumidor.com.br/carreiras","Categoria":"Desenvolvimento"},"id":"5ff0fb3a-1cd9-56f0-80dd-acff4cd6c75b"},{"data":{"Vaga":"Pessoa Dev Desenvolvedora - Trainee","Empresa":"ThoughtWorks","Local":["São Paulo"],"Contato":"https://grnh.se/6f7e27061","Categoria":"Desenvolvimento"},"id":"de3c2af5-b910-5584-abab-4a7016f88508"},{"data":{"Vaga":"Arquiteto de Informação Sênior","Empresa":"ZOLY","Local":["São Paulo"],"Contato":"recrutamento@zoly.com.br","Categoria":"Design"},"id":"52404b6d-0a09-5de0-9571-f3fd51086eca"},{"data":{"Vaga":"iOS Developer","Empresa":"Serasa Consumidor","Local":["Blumenau","São Paulo"],"Contato":"jessica.alves@br.experian.com","Categoria":"Desenvolvimento"},"id":"97dd9674-619f-5295-abd0-affb1195efca"},{"data":{"Vaga":"Pessoa Dev iOS Senior","Empresa":"ThoughtWorks","Local":["São Paulo"],"Contato":"https://grnh.se/cd265d3c1","Categoria":"Desenvolvimento"},"id":"b068ba85-c059-5bd9-943f-9cef88edc771"},{"data":{"Vaga":"UX senior","Empresa":"Serasa Experience","Local":["São Paulo"],"Contato":"leonardo.cichetto@br.experian.com","Categoria":"Design"},"id":"58f55eb5-b79a-51fb-aa83-6c8edfb82e52"},{"data":{"Vaga":"Dev Android Sênior","Empresa":"Foursys","Local":["São Paulo"],"Contato":"recrutamento.unidade2@foursys.com.br","Categoria":"Desenvolvimento"},"id":"42368519-ae2c-5995-98b3-c5e56d2af037"},{"data":{"Vaga":"Senior Frontend Developer","Empresa":"Leads2b","Local":["Curitiba"],"Contato":"https://leads2b.gupy.io/jobs/187347","Categoria":"Desenvolvimento"},"id":"e31455a3-698a-512b-affa-b6ba2b6d9f96"},{"data":{"Vaga":"Businees Development","Empresa":"Serasa Consumidor","Local":["São Paulo"],"Contato":"jessica.alves@br.experian.com","Categoria":"Businees Development"},"id":"7a0aba55-d12e-5287-8d7a-34a83682e629"},{"data":{"Vaga":"Engenheiro de Dados","Empresa":"Elumini","Local":["São Paulo"],"Contato":"http://elumini.enter.jobs/#!/vagas/5e84f5fe9825032500d2b038#top","Categoria":"Desenvolvimento"},"id":"b2247943-33e6-5a8e-a454-96266f5803c3"},{"data":{"Vaga":"Dev Mobile","Empresa":"Grupo Boticário","Local":["São Paulo","Curitiba"],"Contato":"https://www.eufacobonito.com.br/","Categoria":"Desenvolvimento"},"id":"266ac98b-3fa9-58f8-93c6-6b0a577d0fcb"},{"data":{"Vaga":"UI/UX designer","Empresa":"Serasa Consumidor","Local":["Blumenau"],"Contato":"serasaconsumidor.com.br/carreiras","Categoria":"Design"},"id":"7be82d68-a76f-588e-b79e-7e91c6cfcbb1"},{"data":{"Vaga":"Pessoa Dev Android Pleno","Empresa":"ThoughtWorks","Local":["Porto Alegre"],"Contato":"https://grnh.se/472e09471us","Categoria":"Desenvolvimento"},"id":"a2ce1f07-7dec-5115-8d42-f325aab263e5"},{"data":{"Vaga":"Product Design Manager","Empresa":"Next","Local":["São Paulo"],"Contato":"victor.melo@next.b.br","Categoria":"Product Management"},"id":"6eaa2ac0-af10-54ff-a220-e7e12f5f89b8"},{"data":{"Vaga":"UI Designer Pleno","Empresa":"Atech – Embraer Digital","Local":["São Paulo"],"Contato":"uxui@atech.com.br","Categoria":"Design"},"id":"77c029fc-9f04-5510-b45d-3fd70829a9a0"},{"data":{"Vaga":"User Experience Design Specialist","Empresa":"Ioasys","Local":["São Paulo"],"Contato":"https://ioasys.gupy.io/jobs/187456?jobBoardSource=gupy_public_page","Categoria":"Design"},"id":"306ebe34-7dda-5992-9a4d-e5c41f7aeb3e"},{"data":{"Vaga":"Engineering Manager","Empresa":"Origin","Local":["São Paulo"],"Contato":"joao@useorigin.com","Categoria":"Desenvolvimento"},"id":"50627152-13f9-53e4-a843-f56cbf053300"},{"data":{"Vaga":"Desenvolvedor(a) Front end - Presencial ","Empresa":"Olist","Local":["Curitiba","São Paulo"],"Contato":"https://olist.gupy.io/jobs/135206","Categoria":"Desenvolvimento"},"id":"2136e117-4bd1-580f-9b7f-86222646b4d1"},{"data":{"Vaga":"QA","Empresa":"CARGOX","Local":["São Paulo"],"Contato":"https://jobs.kenoby.com/cargox","Categoria":"QA"},"id":"e53c0479-da4c-5c5b-be23-ff8761fdc9f7"},{"data":{"Vaga":"Product Owner","Empresa":"Elumini","Local":["São Paulo"],"Contato":"http://elumini.enter.jobs/#!/vagas/5e67ab39be42c81300fa5cd6#top","Categoria":"Product Management"},"id":"fcd50e97-f013-5beb-b1c9-4a47b839e248"},{"data":{"Vaga":"Tech Lead - Java/angular ","Empresa":"Sempre IT","Local":["São Paulo"],"Contato":"contato@sempreit.com.br","Categoria":"Desenvolvimento"},"id":"821df686-28e6-53c9-a735-98dca0421b3a"},{"data":{"Vaga":"Tech Lead","Empresa":"ZUP","Local":["São Paulo"],"Contato":"https://apply.workable.com/zup/j/80D9EE8C7C/","Categoria":"Desenvolvimento"},"id":"1d637979-2cbb-5c69-9fa3-edbed6203c45"},{"data":{"Vaga":"UX/UI Designer","Empresa":"Proxys group","Local":["São Paulo"],"Contato":"https://proxysgroup.abler.com.br/vagas/ux-ui-designer-217700","Categoria":"Design"},"id":"d689efbf-4b89-5744-8133-07566a5b985a"},{"data":{"Vaga":"Desenvolvedor(a) Front End Angular ","Empresa":"ZUP","Local":["São Paulo"],"Contato":"https://apply.workable.com/zup/j/57EB8EFAC1/","Categoria":"Desenvolvimento"},"id":"46d57c6c-06be-5a3a-9ed3-7145da9b0399"},{"data":{"Vaga":"iOS Developer","Empresa":"Serasa Consumidor","Local":["Blumenau"],"Contato":"serasaconsumidor.com.br/carreiras","Categoria":"Desenvolvimento"},"id":"1d872912-a9ef-57e4-b680-716a77c15dd1"},{"data":{"Vaga":"Engenheiro de Dados II","Empresa":"Tapps Games","Local":["São Paulo"],"Contato":"https://jobs.kenoby.com/tappsgames/job/engenheir-de-dados-ii/5e5e6fd2e131fd34588719fc","Categoria":"Desenvolvimento"},"id":"fbd64242-18fb-5461-bd09-f1c5f17e7c1e"},{"data":{"Vaga":"Product Designer Pl/Sr","Empresa":"SKY Brasil","Local":["São Paulo"],"Contato":"https://www.linkedin.com/jobs/view/1776146884/","Categoria":"Design"},"id":"ee4ff05d-c70d-5a86-a2aa-b3dca37a32d8"},{"data":{"Vaga":"Tech Lead","Empresa":"Sanar","Local":["Salvador","São Paulo","Remoto"],"Contato":"https://jobs.kenoby.com/sanar/job/tech-lead-sanar-medicina/5e3a85efabe6e21941428424","Categoria":"Desenvolvimento"},"id":"fb384368-2c36-5ef3-8fac-263398775f55"},{"data":{"Vaga":"Front End Sênior","Empresa":"Sanar","Local":["Salvador","São Paulo","Remoto"],"Contato":"https://jobs.kenoby.com/sanar/job/desenvolvedora-front-end-senior-sanar-medicina/5e32130982f5eb58563379c2","Categoria":"Desenvolvimento"},"id":"5ba097d8-39e4-549e-a7db-f134a84379a1"},{"data":{"Vaga":"UX Pleno","Empresa":"Bradesco","Local":["São Paulo"],"Contato":"marcel.marques@bradesco.com.br","Categoria":"Design"},"id":"6959ca05-3d93-5559-85ee-ceac875d7f74"},{"data":{"Vaga":"Designer UI/UX","Empresa":"Sanar","Local":["Salvador","São Paulo","Remoto"],"Contato":"https://jobs.kenoby.com/sanar/job/designer-uiux/5e3a2deaccc016193b4e4b6d","Categoria":"Design"},"id":"954484b9-c9f0-5647-9d82-21fb2c0ca151"},{"data":{"Vaga":"Pessoa Dev Android Senior","Empresa":"ThoughtWorks","Local":["Belo Horizonte"],"Contato":"https://grnh.se/5c073c851us","Categoria":"Desenvolvimento"},"id":"9335b519-14c2-5d7a-a023-3ba337b7bae3"},{"data":{"Vaga":"Product Manager","Empresa":"Bradesco","Local":["São José dos Campos"],"Contato":"marcel.marques@bradesco.com.br","Categoria":"Product Management"},"id":"cce0deaa-290d-5fd9-8cfc-89b6dbdb8369"},{"data":{"Vaga":"Pessoa Dev Front-end Pleno","Empresa":"ThoughtWorks","Local":["Recife"],"Contato":"https://grnh.se/962b507f1us","Categoria":"Desenvolvimento"},"id":"3b9337c0-8ab7-52e4-ba06-470bf1aeff8a"},{"data":{"Vaga":"Android Developer","Empresa":"Serasa Consumidor","Local":["Blumenau"],"Contato":"serasaconsumidor.com.br/carreiras","Categoria":"Desenvolvimento"},"id":"68c6efb5-aafa-5ded-9ba1-e054609e4b8e"},{"data":{"Vaga":"UX Designer | RJ - Sr","Empresa":"Globo.com ","Local":["Rio de Janeiro"],"Contato":"https://talentos.globo.com/#/oportunidades/ux-designer-rj/mp038nh","Categoria":"Design"},"id":"bbb7d8c7-1079-5400-a100-5aeccf35db6b"},{"data":{"Vaga":"Back End Jr","Empresa":"Sanar","Local":["Salvador","São Paulo","Remoto"],"Contato":"https://jobs.kenoby.com/sanar/job/desenvolvedora-back-end-junior-sanar-medicina/5e2a109a87347b5a828ca338","Categoria":"Desenvolvimento"},"id":"d20f85cd-c36f-5752-96e0-f1a54e4a38fa"},{"data":{"Vaga":"Product Manager","Empresa":"Origin","Local":["São Paulo"],"Contato":"joao@useorigin.com","Categoria":"Product Management"},"id":"c8d56ac0-7d52-5e25-a80b-94d3c9951551"},{"data":{"Vaga":"CTO","Empresa":"ZUP Innovation","Local":["Uberlandia","Campinas","São Paulo","Joinville","Belo Horizonte"],"Contato":"https://www.zup.com.br/vagas","Categoria":"Desenvolvimento"},"id":"5a642f4f-7266-5d0b-b2a8-f511cf24b9e3"},{"data":{"Vaga":"Desenvolvedor PL e SR","Empresa":"Zenvia","Local":["Porto Alegre"],"Contato":"https://zenvia.gupy.io/","Categoria":"Desenvolvimento"},"id":"ba2429ce-a3fb-50c7-a3d1-8fd039698e41"},{"data":{"Vaga":"Desenvolvedor/Desenvolvedora Backend","Empresa":"Delivery Much","Local":["Florianópolis"],"Contato":"https://jobs.kenoby.com/deliverymuch/job/desenvolvedordesenvolvedora-backend-8-vagas/5e7f9f98b873f256d135daa0","Categoria":"Desenvolvimento"},"id":"75194e53-4ceb-50e1-9d57-3d314fa7e9e5"},{"data":{"Vaga":"Dev Front End Sênior","Empresa":"Foursys","Local":["São Paulo"],"Contato":"recrutamento.unidade2@foursys.com.br","Categoria":"Desenvolvimento"},"id":"244ca811-a55f-5a4a-9cb6-de7b8128dc25"},{"data":{"Vaga":"Software Analyst","Empresa":"Serasa Consumidor","Local":["Blumenau"],"Contato":"jessica.alves@br.experian.com","Categoria":"Desenvolvimento"},"id":"4936517b-f454-5f1b-a0f1-c286597292f4"},{"data":{"Vaga":"Coordenador de UX e SEO","Empresa":"Marisa S.A.","Local":["São Paulo"],"Contato":"https://site.vagas.com.br/PagVagaDirSS.asp?v=2047670&pp=https%3A//site.vagas.com.br/GoHome.asp%3Fv%3D2047670%26j%3Dt%26sslon%3D1&wiw=1687","Categoria":"Design"},"id":"82548776-7bea-53e3-ac87-31d89dccbbb7"},{"data":{"Vaga":"UX | UI Designer Sênior – SQUAD CTO Digital","Empresa":"Tivit","Local":["São Paulo"],"Contato":"https://jobs.kenoby.com/tivit/job/ux-ui-design-senior-squad-cto-digital/5e839838d050a21886aeba09","Categoria":"Design"},"id":"cbf263d9-0981-53c0-9754-6f0a73fa6ca7"},{"data":{"Vaga":"Back End Python","Empresa":"The Hive Brasil","Local":["São Paulo"],"Contato":"https://www.linkedin.com/jobs/view/1772037638/?refId=1350387711585962361819&trk=d_flagship3_company","Categoria":"Desenvolvimento"},"id":"c49490bf-6ff1-5d11-bf5c-effaba48736a"},{"data":{"Vaga":"ANDROID DEVELOPER KOTLIN PLENO","Empresa":"CARGOX","Local":["São Paulo"],"Contato":"https://jobs.kenoby.com/cargox","Categoria":"Desenvolvimento"},"id":"31ada4e1-f501-5f58-8f41-a876dba8be2a"},{"data":{"Vaga":"Pessoa Dev Android Pleno","Empresa":"ThoughtWorks","Local":["Belo Horizonte"],"Contato":"https://grnh.se/1f24f2781us","Categoria":"Desenvolvimento"},"id":"8d03e7ad-0921-58f4-a229-bc05d6fa1eb0"},{"data":{"Vaga":"Desenvolvedor(a) Python - Presencial ","Empresa":"Olist","Local":["Curitiba","São Paulo"],"Contato":"https://olist.gupy.io/jobs/118828","Categoria":"Desenvolvimento"},"id":"b7fac0f1-a3cf-5b38-9041-56171f9cf32c"},{"data":{"Vaga":"Desenvolvedor MAGENTO PLENO E SR","Empresa":"RD (RAIA DROGASIL)","Local":["São Paulo"],"Contato":"arigon@rd.com.br","Categoria":"Desenvolvimento"},"id":"3d6a02dd-1a84-51a4-8419-83b56d848628"},{"data":{"Vaga":"Senior Fullstack Developer","Empresa":"Leads2b","Local":["Curitiba"],"Contato":"https://leads2b.gupy.io/jobs/198381","Categoria":"Desenvolvimento"},"id":"cb3d4165-7991-530f-b748-55ef03bd9519"},{"data":{"Vaga":"Pessoa Dev Front-end Senior","Empresa":"ThoughtWorks","Local":["Porto Alegre"],"Contato":"https://grnh.se/2ffb22091us","Categoria":"Desenvolvimento"},"id":"6eac1e76-2001-5160-b7ca-745df449bac8"},{"data":{"Vaga":"Front End Pleno","Empresa":"Sanar","Local":["Salvador","São Paulo","Remoto"],"Contato":"https://jobs.kenoby.com/sanar/job/desenvolvedora-front-end-pleno-sanar-medicina/5e32124682f5eb5856337799","Categoria":"Desenvolvimento"},"id":"3022e8d8-d195-5bb7-a674-08f373a3c23d"},{"data":{"Vaga":"Senior Product Researcher","Empresa":"Runtastic","Local":["Austria"],"Contato":"eugenio.grigolon@runtastic.com","Categoria":"Design"},"id":"7964bd62-f91f-5fcf-9601-d93b87c5e190"},{"data":{"Vaga":"Desenvolvedor(a) Backend Java ","Empresa":"ZUP","Local":["São Paulo"],"Contato":"https://apply.workable.com/zup/j/7814994F83/","Categoria":"Desenvolvimento"},"id":"a10868c9-35b8-52ef-83dd-8245b1dcc570"},{"data":{"Vaga":"UX Writer","Empresa":"Next","Local":["São Paulo"],"Contato":"victor.melo@next.b.br","Categoria":"Design"},"id":"1710aa3a-fc84-5d63-a89c-efe1211ae543"},{"data":{"Vaga":"SCRUM Master","Empresa":"Elumini","Local":["São Paulo"],"Contato":"http://elumini.enter.jobs/#!/vagas/5e4e8cfc81eda61300ad9803#top","Categoria":"Product Management"},"id":"4c8e07b1-1a92-5086-8f79-ea6ba0094dc1"},{"data":{"Vaga":"Cyber Security","Empresa":"Serasa Consumidor","Local":["São Paulo"],"Contato":"serasaconsumidor.com.br/carreiras","Categoria":"Desenvolvimento"},"id":"efb654ac-641e-584a-b42e-7ff716958e7a"},{"data":{"Vaga":"Desenvolvedor GO - Presencial","Empresa":"Olist","Local":["São Paulo"],"Contato":"https://olist.gupy.io/jobs/98273","Categoria":"Desenvolvimento"},"id":"9c5ffded-9fb6-5b51-aa34-beb410fbb11d"},{"data":{"Vaga":"Dev Front End","Empresa":"Grupo Boticário","Local":["São Paulo","Curitiba"],"Contato":"https://www.eufacobonito.com.br/","Categoria":"Desenvolvimento"},"id":"444374c5-5f58-50e5-828e-76ca7e00b653"},{"data":{"Vaga":"Front & Back-end Tech Lead","Empresa":"Origin","Local":["São Paulo"],"Contato":"joao@useorigin.com","Categoria":"Desenvolvimento"},"id":"646f7f31-5fa4-5791-b6bb-a1ac639645d0"},{"data":{"Vaga":"Cientista de Dados","Empresa":"Geofusion","Local":["São Paulo"],"Contato":"https://www.vagas.com.br/empregos/geofusion","Categoria":"Desenvolvimento"},"id":"d66fa3bb-31d3-5bc5-94dc-325dc916d5aa"},{"data":{"Vaga":"Backend Developer (Python, Java, Node.js, PHP)","Empresa":"Serasa Consumidor","Local":["Blumenau"],"Contato":"serasaconsumidor.com.br/carreiras","Categoria":"Desenvolvimento"},"id":"3d3749b0-1267-5476-9f28-76d556d20828"},{"data":{"Vaga":"PO","Empresa":"CARGOX","Local":["São Paulo"],"Contato":"https://jobs.kenoby.com/cargox","Categoria":"Product Management"},"id":"0dfce2cd-ee4e-5c6f-ba7f-3e71ef13f275"},{"data":{"Vaga":"Senior Product Designer","Empresa":"Rede D'Or São Luiz","Local":["Rio de Janeiro"],"Contato":"carlos.pgama@rededor.com.br","Categoria":"Design"},"id":"26c59deb-4780-5ca1-92df-a783d9e39366"},{"data":{"Vaga":"Pessoa Dev Back-end Pleno","Empresa":"ThoughtWorks","Local":["Belo Horizonte"],"Contato":"https://grnh.se/2af2124e1us","Categoria":"Desenvolvimento"},"id":"f9cf25e7-775b-5c2d-9b4b-df31c331bd1d"},{"data":{"Vaga":"UX/UI Designer ","Empresa":"Delivery Much","Local":["Florianópolis"],"Contato":"https://jobs.kenoby.com/deliverymuch/job/uxui-designer/5e81c6710fcc3456cb05a2c7","Categoria":"Design"},"id":"d580fba2-80a2-59eb-82f0-80ccc1cd0e72"},{"data":{"Vaga":"Product Owner","Empresa":"Serasa Consumidor","Local":["Blumenau"],"Contato":"serasaconsumidor.com.br/carreiras","Categoria":"Product Management"},"id":"925c4b65-effc-5f77-aa45-43b8c058df96"},{"data":{"Vaga":"SOFTWARE ENGINEER SÊNIOR","Empresa":"CARGOX","Local":["São Paulo"],"Contato":"https://jobs.kenoby.com/cargox","Categoria":"Desenvolvimento"},"id":"6774bcbe-a756-5baa-8189-0b767e8dfad5"}],"categories":[{"fieldValue":"Businees Development","totalCount":1},{"fieldValue":"Desenvolvimento","totalCount":128},{"fieldValue":"Design","totalCount":52},{"fieldValue":"Outras","totalCount":4},{"fieldValue":"Product Management","totalCount":17},{"fieldValue":"QA","totalCount":7},{"fieldValue":"SEO","totalCount":1}],"local":[{"fieldValue":"Austria","totalCount":1},{"fieldValue":"Bahia","totalCount":1},{"fieldValue":"Belo Horizonte","totalCount":17},{"fieldValue":"Blumenau","totalCount":19},{"fieldValue":"Brasília","totalCount":3},{"fieldValue":"Buenos Aires","totalCount":4},{"fieldValue":"Campinas","totalCount":5},{"fieldValue":"Cidade do México","totalCount":4},{"fieldValue":"Curitiba","totalCount":11},{"fieldValue":"Florianópolis","totalCount":6},{"fieldValue":"Joinville","totalCount":5},{"fieldValue":"Manaus","totalCount":1},{"fieldValue":"Porto Alegre","totalCount":13},{"fieldValue":"Recife","totalCount":9},{"fieldValue":"Remoto","totalCount":16},{"fieldValue":"Rio de Janeiro","totalCount":3},{"fieldValue":"Salvador","totalCount":14},{"fieldValue":"São José dos Campos","totalCount":5},{"fieldValue":"São Paulo","totalCount":135},{"fieldValue":"Uberlandia","totalCount":5}]},"site":{"siteMetadata":{"title":"vagas.cc","description":"Uma iniciativa que tem por objetivo trazer a esperança de um novo emprego, mesmo em meio à incerteza da pandemia.","heroHeadline":"Vagas de Tecnologia","formUrl":"https://airtable.com/shrcFKFGDq6WcGZkJ","footer":"Projeto desenvolvido por <a href=\"https://edkf.com.br\" target=\"_blank\">@edkf</a>. Agradecimento especial à <a href=\"https://kaisermann.me/\" target=\"_blank\">@kiwistian</a> e <a href=\"https://www.linkedin.com/in/leilacangussu/\" target=\"_blank\">@LeilaCristina</a>. <br /> Para reportar um erro, mandar duvidas ou sugestões, enviar email para <a href=\"mailto:hello@edkf.com.br\">hello@edkf.com.br</a>."}}}}